triton_copilot/__init__.py
triton_copilot/build_services.py
triton_copilot/constants.py
triton_copilot/init_services.py
triton_copilot/main.py
triton_copilot/run_services.py
triton_copilot/template/1/model.py
triton_copilot/template/Dockerfile
triton_copilot/triton_services.py
triton_copilot/utils.py
triton_copilot/validate.py
triton_copilot-0.1.5.dist-info/METADATA
triton_copilot-0.1.5.dist-info/WHEEL
triton_copilot-0.1.5.dist-info/entry_points.txt
triton_copilot-0.1.5.dist-info/RECORD
