Metadata-Version: 2.1
Name: triton-copilot
Version: 0.1.5
Summary: 
Author: Your Name
Author-email: you@example.com
Requires-Python: >=3.8,<4.0
Classifier: Programming Language :: Python :: 3
Classifier: Programming Language :: Python :: 3.8
Classifier: Programming Language :: Python :: 3.9
Classifier: Programming Language :: Python :: 3.10
Classifier: Programming Language :: Python :: 3.11
Classifier: Programming Language :: Python :: 3.12
Requires-Dist: anthropic (==0.23.1)
Requires-Dist: openai (==1.16.2)
Requires-Dist: rich (==13.7.1)
Requires-Dist: typer[all] (>=0.12.1,<0.13.0)
